envtoolkit/__init__.py
envtoolkit/colors.py
envtoolkit/date.py
envtoolkit/map.py
envtoolkit/nc.py
envtoolkit/spectral.py
envtoolkit/ts.py
envtoolkit-1.0.1.dist-info/LICENSE
envtoolkit-1.0.1.dist-info/METADATA
envtoolkit-1.0.1.dist-info/WHEEL
envtoolkit-1.0.1.dist-info/top_level.txt
envtoolkit-1.0.1.dist-info/RECORD
